LICENSE
MANIFEST.in
README.rst
setup.py
src/compapp/__init__.py
src/compapp/__main__.py
src/compapp/apps.py
src/compapp/base.py
src/compapp/cli.py
src/compapp/conftest.py
src/compapp/core.py
src/compapp/executables.py
src/compapp/interactive.py
src/compapp/interface.py
src/compapp/loader.py
src/compapp/parser.py
src/compapp/strict.py
src/compapp/variator.py
src/compapp.egg-info/PKG-INFO
src/compapp.egg-info/SOURCES.txt
src/compapp.egg-info/dependency_links.txt
src/compapp.egg-info/entry_points.txt
src/compapp.egg-info/top_level.txt
src/compapp/descriptors/__init__.py
src/compapp/descriptors/dynamic_class.py
src/compapp/descriptors/links.py
src/compapp/descriptors/misc.py
src/compapp/descriptors/traits.py
src/compapp/descriptors/tests/__init__.py
src/compapp/descriptors/tests/test_complex.py
src/compapp/descriptors/tests/test_dynamic_class.py
src/compapp/descriptors/tests/test_or.py
src/compapp/descriptors/tests/test_params.py
src/compapp/plugins/__init__.py
src/compapp/plugins/datastores.py
src/compapp/plugins/metastore.py
src/compapp/plugins/misc.py
src/compapp/plugins/programinfo.py
src/compapp/plugins/recorders.py
src/compapp/plugins/sysinfo.py
src/compapp/plugins/timing.py
src/compapp/plugins/vcs.py
src/compapp/plugins/tests/__init__.py
src/compapp/plugins/tests/test_autoupstreams.py
src/compapp/plugins/tests/test_datastores.py
src/compapp/plugins/tests/test_logger.py
src/compapp/samples/__init__.py
src/compapp/samples/named_figure.py
src/compapp/samples/pluggable_plotter_exec.py
src/compapp/samples/pluggable_plotter_link.py
src/compapp/samples/simple_plots.py
src/compapp/tests/__init__.py
src/compapp/tests/test_apps.py
src/compapp/tests/test_base.py
src/compapp/tests/test_core.py
src/compapp/tests/test_executable.py
src/compapp/tests/test_parametric.py
src/compapp/tests/test_parser.py
src/compapp/tests/test_samples.py
src/compapp/tests/test_strict.py
src/compapp/tests/test_variator.py
src/compapp/utils/__init__.py
src/compapp/utils/files.py
src/compapp/utils/importer.py