Metadata-Version: 1.1
Name: compapp
Version: 0.1.0.dev1
Summary: A framework for simulations and data analysis
Home-page: https://github.com/tkf/compapp
Author: Takafumi Arakaki
Author-email: aka.tkf@gmail.com
License: BSD-2-Clause
Keywords: numerical simulation,research
Platform: UNKNOWN
Classifier: Development Status :: 2 - Pre-Alpha
Classifier: License :: OSI Approved :: BSD License
